{
  "$schema": "https://developer.microsoft.com/json-schemas/spfx-build/package-solution.schema.json",
  "solution": {
    "name": "graph-api-demo-client-side-solution",
    "id": "a4ecde36-0199-4fb3-a7ec-3353a5adce6f",
    "version": "1.0.0.0",
    "includeClientSideAssets": true,
    "skipFeatureDeployment": true,
    "isDomainIsolated": false,
    "developer": {
      "name": "",
      "websiteUrl": "",
      "privacyUrl": "",
      "termsOfUseUrl": "",
      "mpnId": "Undefined-1.21.1"
    },
    "metadata": {
      "shortDescription": {
        "default": "graph-api-demo description"
      },
      "longDescription": {
        "default": "graph-api-demo description"
      },
      "screenshotPaths": [],
      "videoUrl": "",
      "categories": []
    },
    "features": [
      {
        "title": "graph-api-demo Feature",
        "description": "The feature that activates elements of the graph-api-demo solution.",
        "id": "1e30cacc-02ec-4376-b435-c6a6f105f77b",
        "version": "1.0.0.0"
      }
    ]
  },
  "paths": {
    "zippedPackage": "solution/graph-api-demo.sppkg"
  }
}
